{
	"cmake" : 
	{
		"generator" : 
		{
			"multiConfig" : false,
			"name" : "Ninja"
		},
		"paths" : 
		{
			"cmake" : "/Users/jeonghoeheon/Library/Android/sdk/cmake/3.22.1/bin/cmake",
			"cpack" : "/Users/jeonghoeheon/Library/Android/sdk/cmake/3.22.1/bin/cpack",
			"ctest" : "/Users/jeonghoeheon/Library/Android/sdk/cmake/3.22.1/bin/ctest",
			"root" : "/Users/jeonghoeheon/Library/Android/sdk/cmake/3.22.1/share/cmake-3.22"
		},
		"version" : 
		{
			"isDirty" : false,
			"major" : 3,
			"minor" : 22,
			"patch" : 1,
			"string" : "3.22.1-g37088a8",
			"suffix" : "g37088a8"
		}
	},
	"objects" : 
	[
		{
			"jsonFile" : "codemodel-v2-84f6ee6a5fd48c43eec4.json",
			"kind" : "codemodel",
			"version" : 
			{
				"major" : 2,
				"minor" : 3
			}
		},
		{
			"jsonFile" : "cache-v2-ba587eb454f91a4cd775.json",
			"kind" : "cache",
			"version" : 
			{
				"major" : 2,
				"minor" : 0
			}
		},
		{
			"jsonFile" : "cmakeFiles-v1-f8a15c7088b5ebb3da2e.json",
			"kind" : "cmakeFiles",
			"version" : 
			{
				"major" : 1,
				"minor" : 0
			}
		}
	],
	"reply" : 
	{
		"client-agp" : 
		{
			"cache-v2" : 
			{
				"jsonFile" : "cache-v2-ba587eb454f91a4cd775.json",
				"kind" : "cache",
				"version" : 
				{
					"major" : 2,
					"minor" : 0
				}
			},
			"cmakeFiles-v1" : 
			{
				"jsonFile" : "cmakeFiles-v1-f8a15c7088b5ebb3da2e.json",
				"kind" : "cmakeFiles",
				"version" : 
				{
					"major" : 1,
					"minor" : 0
				}
			},
			"codemodel-v2" : 
			{
				"jsonFile" : "codemodel-v2-84f6ee6a5fd48c43eec4.json",
				"kind" : "codemodel",
				"version" : 
				{
					"major" : 2,
					"minor" : 3
				}
			}
		}
	}
}
